Metadata-Version: 2.1
Name: tsc-notif
Version: 0.5
Summary: 自动通知
Home-page: https://github.com/aitsc/tsc-notif
Author: aitsc
License: UNKNOWN
Platform: UNKNOWN
Requires-Python: >=3.7
License-File: LICENSE
